{
  "source": "douyin",
  "fetchedAt": "2026-03-05T01:06:46.204Z",
  "items": [
    {
      "id": "douyin-0",
      "title": "十四届全国人大四次会议开幕会",
      "url": "https://www.douyin.com/search/%E5%8D%81%E5%9B%9B%E5%B1%8A%E5%85%A8%E5%9B%BD%E4%BA%BA%E5%A4%A7%E5%9B%9B%E6%AC%A1%E4%BC%9A%E8%AE%AE%E5%BC%80%E5%B9%95%E4%BC%9A",
      "source": "douyin",
      "category": "trending",
      "hotScore": 11312838,
      "extra": {
        "label": 1,
        "videoCount": 1
      }
    },
    {
      "id": "douyin-1",
      "title": "全国两会首场代表通道",
      "url": "https://www.douyin.com/search/%E5%85%A8%E5%9B%BD%E4%B8%A4%E4%BC%9A%E9%A6%96%E5%9C%BA%E4%BB%A3%E8%A1%A8%E9%80%9A%E9%81%93",
      "source": "douyin",
      "category": "trending",
      "hotScore": 11242064,
      "extra": {
        "label": 1,
        "videoCount": 2
      }
    },
    {
      "id": "douyin-2",
      "title": "中国量子计算稳居国际第一方阵",
      "url": "https://www.douyin.com/search/%E4%B8%AD%E5%9B%BD%E9%87%8F%E5%AD%90%E8%AE%A1%E7%AE%97%E7%A8%B3%E5%B1%85%E5%9B%BD%E9%99%85%E7%AC%AC%E4%B8%80%E6%96%B9%E9%98%B5",
      "source": "douyin",
      "category": "trending",
      "hotScore": 11004557,
      "extra": {
        "label": 3,
        "videoCount": 2
      }
    },
    {
      "id": "douyin-3",
      "title": "建议合理增加下半年节假日",
      "url": "https://www.douyin.com/search/%E5%BB%BA%E8%AE%AE%E5%90%88%E7%90%86%E5%A2%9E%E5%8A%A0%E4%B8%8B%E5%8D%8A%E5%B9%B4%E8%8A%82%E5%81%87%E6%97%A5",
      "source": "douyin",
      "category": "trending",
      "hotScore": 10795358,
      "extra": {
        "label": 1,
        "videoCount": 2
      }
    },
    {
      "id": "douyin-4",
      "title": "中央政治局原常委宋平逝世",
      "url": "https://www.douyin.com/search/%E4%B8%AD%E5%A4%AE%E6%94%BF%E6%B2%BB%E5%B1%80%E5%8E%9F%E5%B8%B8%E5%A7%94%E5%AE%8B%E5%B9%B3%E9%80%9D%E4%B8%96",
      "source": "douyin",
      "category": "trending",
      "hotScore": 10208680,
      "extra": {
        "label": 0,
        "videoCount": 1
      }
    },
    {
      "id": "douyin-5",
      "title": "建议整治精神病医院骗保乱象",
      "url": "https://www.douyin.com/search/%E5%BB%BA%E8%AE%AE%E6%95%B4%E6%B2%BB%E7%B2%BE%E7%A5%9E%E7%97%85%E5%8C%BB%E9%99%A2%E9%AA%97%E4%BF%9D%E4%B9%B1%E8%B1%A1",
      "source": "douyin",
      "category": "trending",
      "hotScore": 10203960,
      "extra": {
        "label": 0,
        "videoCount": 1
      }
    },
    {
      "id": "douyin-6",
      "title": "博士用十年为机器人注入灵魂",
      "url": "https://www.douyin.com/search/%E5%8D%9A%E5%A3%AB%E7%94%A8%E5%8D%81%E5%B9%B4%E4%B8%BA%E6%9C%BA%E5%99%A8%E4%BA%BA%E6%B3%A8%E5%85%A5%E7%81%B5%E9%AD%82",
      "source": "douyin",
      "category": "trending",
      "hotScore": 9121126,
      "extra": {
        "label": 0,
        "videoCount": 2
      }
    },
    {
      "id": "douyin-7",
      "title": "建议废除劳务派遣制度",
      "url": "https://www.douyin.com/search/%E5%BB%BA%E8%AE%AE%E5%BA%9F%E9%99%A4%E5%8A%B3%E5%8A%A1%E6%B4%BE%E9%81%A3%E5%88%B6%E5%BA%A6",
      "source": "douyin",
      "category": "trending",
      "hotScore": 8772838,
      "extra": {
        "label": 3,
        "videoCount": 3
      }
    },
    {
      "id": "douyin-8",
      "title": "我国将制定托育服务法等法律",
      "url": "https://www.douyin.com/search/%E6%88%91%E5%9B%BD%E5%B0%86%E5%88%B6%E5%AE%9A%E6%89%98%E8%82%B2%E6%9C%8D%E5%8A%A1%E6%B3%95%E7%AD%89%E6%B3%95%E5%BE%8B",
      "source": "douyin",
      "category": "trending",
      "hotScore": 8436230,
      "extra": {
        "label": 3,
        "videoCount": 2
      }
    },
    {
      "id": "douyin-9",
      "title": "建议提高个税起征点至8000或1万",
      "url": "https://www.douyin.com/search/%E5%BB%BA%E8%AE%AE%E6%8F%90%E9%AB%98%E4%B8%AA%E7%A8%8E%E8%B5%B7%E5%BE%81%E7%82%B9%E8%87%B38000%E6%88%961%E4%B8%87",
      "source": "douyin",
      "category": "trending",
      "hotScore": 7967894,
      "extra": {
        "label": 0,
        "videoCount": 3
      }
    },
    {
      "id": "douyin-10",
      "title": "今天惊蛰",
      "url": "https://www.douyin.com/search/%E4%BB%8A%E5%A4%A9%E6%83%8A%E8%9B%B0",
      "source": "douyin",
      "category": "trending",
      "hotScore": 7849157,
      "extra": {
        "label": 1,
        "videoCount": 4
      }
    },
    {
      "id": "douyin-11",
      "title": "美国多地爆发反战抗议活动",
      "url": "https://www.douyin.com/search/%E7%BE%8E%E5%9B%BD%E5%A4%9A%E5%9C%B0%E7%88%86%E5%8F%91%E5%8F%8D%E6%88%98%E6%8A%97%E8%AE%AE%E6%B4%BB%E5%8A%A8",
      "source": "douyin",
      "category": "trending",
      "hotScore": 7839611,
      "extra": {
        "label": 3,
        "videoCount": 4
      }
    },
    {
      "id": "douyin-12",
      "title": "让豆包给我取个网名",
      "url": "https://www.douyin.com/search/%E8%AE%A9%E8%B1%86%E5%8C%85%E7%BB%99%E6%88%91%E5%8F%96%E4%B8%AA%E7%BD%91%E5%90%8D",
      "source": "douyin",
      "category": "trending",
      "hotScore": 7836118,
      "extra": {
        "label": 17,
        "videoCount": 10
      }
    },
    {
      "id": "douyin-13",
      "title": "苹果春季发布会",
      "url": "https://www.douyin.com/search/%E8%8B%B9%E6%9E%9C%E6%98%A5%E5%AD%A3%E5%8F%91%E5%B8%83%E4%BC%9A",
      "source": "douyin",
      "category": "trending",
      "hotScore": 7829077,
      "extra": {
        "label": 0,
        "videoCount": 5
      }
    },
    {
      "id": "douyin-14",
      "title": "纽卡2:1曼联",
      "url": "https://www.douyin.com/search/%E7%BA%BD%E5%8D%A12%3A1%E6%9B%BC%E8%81%94",
      "source": "douyin",
      "category": "trending",
      "hotScore": 7827401,
      "extra": {
        "label": 1,
        "videoCount": 1
      }
    }
  ]
}